
[
    {
        "key": "sb",
        "value": "sm3MaEMseVwPw7hLilk60Ote",
        "domain": "facebook.com",
        "path": "/",
        "hostOnly": false,
        "creation": "2025-10-29T08:57:07.982Z",
        "lastAccessed": "2025-10-29T08:57:07.983Z"
    },
    {
        "key": "vpd",
        "value": "v1%3B664x360x2",
        "domain": "facebook.com",
        "path": "/",
        "hostOnly": false,
        "creation": "2025-10-29T08:57:07.983Z",
        "lastAccessed": "2025-10-29T08:57:07.983Z"
    },
    {
        "key": "ps_l",
        "value": "1",
        "domain": "facebook.com",
        "path": "/",
        "hostOnly": false,
        "creation": "2025-10-29T08:57:07.983Z",
        "lastAccessed": "2025-10-29T08:57:07.983Z"
    },
    {
        "key": "ps_n",
        "value": "1",
        "domain": "facebook.com",
        "path": "/",
        "hostOnly": false,
        "creation": "2025-10-29T08:57:07.983Z",
        "lastAccessed": "2025-10-29T08:57:07.983Z"
    },
    {
        "key": "datr",
        "value": "b478aBraejBLYDbGVuHyfOBm",
        "domain": "facebook.com",
        "path": "/",
        "hostOnly": false,
        "creation": "2025-10-29T08:57:07.983Z",
        "lastAccessed": "2025-10-29T08:57:07.983Z"
    },
    {
        "key": "c_user",
        "value": "61574877431774",
        "domain": "facebook.com",
        "path": "/",
        "hostOnly": false,
        "creation": "2025-10-29T08:57:07.983Z",
        "lastAccessed": "2025-10-29T08:57:07.983Z"
    },
    {
        "key": "xs",
        "value": "11%3AITOPAfqmQNshtQ%3A2%3A1761725087%3A-1%3A-1",
        "domain": "facebook.com",
        "path": "/",
        "hostOnly": false,
        "creation": "2025-10-29T08:57:07.983Z",
        "lastAccessed": "2025-10-29T08:57:07.983Z"
    },
    {
        "key": "pas",
        "value": "61574877431774%3AsHXUV3Kgad",
        "domain": "facebook.com",
        "path": "/",
        "hostOnly": false,
        "creation": "2025-10-29T08:57:07.983Z",
        "lastAccessed": "2025-10-29T08:57:07.983Z"
    },
    {
        "key": "locale",
        "value": "en_US",
        "domain": "facebook.com",
        "path": "/",
        "hostOnly": false,
        "creation": "2025-10-29T08:57:07.983Z",
        "lastAccessed": "2025-10-29T08:57:07.983Z"
    },
    {
        "key": "fr",
        "value": "0lF2nvS227Us2JcjK.AWcFBnAT2ylSZ4XHjW8gLNe5kqBR0H-Yh1P5XtKxLHX3fbQBUtU.BozG2y..AAA.0.0.BpAcrC.AWfrjXIelaunykoNpF_-OJcj8bo",
        "domain": "facebook.com",
        "path": "/",
        "hostOnly": false,
        "creation": "2025-10-29T08:57:07.983Z",
        "lastAccessed": "2025-10-29T08:57:07.983Z"
    },
    {
        "key": "fbl_st",
        "value": "100629701%3BT%3A29362085",
        "domain": "facebook.com",
        "path": "/",
        "hostOnly": false,
        "creation": "2025-10-29T08:57:07.983Z",
        "lastAccessed": "2025-10-29T08:57:07.983Z"
    },
    {
        "key": "wl_cbv",
        "value": "v2%3Bclient_version%3A2968%3Btimestamp%3A1761725122",
        "domain": "facebook.com",
        "path": "/",
        "hostOnly": false,
        "creation": "2025-10-29T08:57:07.983Z",
        "lastAccessed": "2025-10-29T08:57:07.983Z"
    }
]
